iflow_mcp_nexonco_mcp-0.1.11.dist-info/licenses/LICENSE
nexonco/api.py
nexonco/query.py
nexonco/server.py
iflow_mcp_nexonco_mcp-0.1.11.dist-info/METADATA
iflow_mcp_nexonco_mcp-0.1.11.dist-info/WHEEL
iflow_mcp_nexonco_mcp-0.1.11.dist-info/entry_points.txt
iflow_mcp_nexonco_mcp-0.1.11.dist-info/top_level.txt
iflow_mcp_nexonco_mcp-0.1.11.dist-info/RECORD
